{
    "profiles": [
        {
            "complex_modifications": {
                "rules": [
                    {
                        "description": "Change caps_lock to left_control if pressed with other keys, change caps_lock to escape if pressed alone.",
                        "manipulators": [
                            {
                                "from": {
                                    "key_code": "caps_lock",
                                    "modifiers": { "optional": ["any"] }
                                },
                                "to": [{ "key_code": "left_control" }],
                                "to_if_alone": [{ "key_code": "escape" }],
                                "type": "basic"
                            }
                        ]
                    }
                ]
            },
            "devices": [
                {
                    "identifiers": {
                        "is_keyboard": true,
                        "is_pointing_device": true,
                        "product_id": 8705,
                        "vendor_id": 4617
                    },
                    "ignore": false,
                    "ignore_vendor_events": true,
                    "treat_as_built_in_keyboard": true
                },
                {
                    "identifiers": {
                        "is_pointing_device": true,
                        "product_id": 8705,
                        "vendor_id": 4617
                    },
                    "ignore": false,
                    "ignore_vendor_events": true
                }
            ],
            "name": "Default profile",
            "selected": true,
            "virtual_hid_keyboard": { "keyboard_type_v2": "ansi" }
        }
    ],
    "rules": [
        {
            "description": "Change Caps Lock to Control when held, Escape when tapped",
            "manipulators": [
                {
                    "from": {
                        "key_code": "caps_lock",
                        "modifiers": { "optional": ["any"] }
                    },
                    "parameters": { "basic.to_if_alone_timeout_milliseconds": 100 },
                    "to": [{ "key_code": "left_control" }],
                    "to_if_alone": [{ "key_code": "escape" }],
                    "type": "basic"
                }
            ]
        }
    ],
    "title": "Caps Lock to Control/Escape"
}